yamldb/YamlDB.py
yamldb/__init__.py
yamldb/util.py
yamldb-1.0.4.dist-info/LICENSE
yamldb-1.0.4.dist-info/METADATA
yamldb-1.0.4.dist-info/WHEEL
yamldb-1.0.4.dist-info/top_level.txt
yamldb-1.0.4.dist-info/RECORD
